mistake/__init__.py
mistake/localize.py
mistake/main.py
mistake/runner.py
mistake/utils.py
mistake/parser/__init__.py
mistake/parser/ast.py
mistake/parser/parser.py
mistake/parser/errors/__init__.py
mistake/parser/errors/parser_errors.py
mistake/runtime/__init__.py
mistake/runtime/environment.py
mistake/runtime/interpreter.py
mistake/runtime/runtime_types.py
mistake/runtime/errors/__init__.py
mistake/runtime/errors/runtime_errors.py
mistake/runtime/stdlib/__init__.py
mistake/runtime/stdlib/airtable_api.py
mistake/runtime/stdlib/networking.py
mistake/runtime/stdlib/std_funcs.py
mistake/runtime/stdlib/vulkan_api.py
mistake/tests/test_interpreter.py
mistake/tokenizer/__init__.py
mistake/tokenizer/lexer.py
mistake/tokenizer/token.py
mistake_lang-0.2.0.dist-info/LICENSE
mistake_lang-0.2.0.dist-info/METADATA
mistake_lang-0.2.0.dist-info/WHEEL
mistake_lang-0.2.0.dist-info/entry_points.txt
mistake_lang-0.2.0.dist-info/top_level.txt
mistake_lang-0.2.0.dist-info/RECORD
