Metadata-Version: 2.2
Name: mistake-lang
Version: 0.2.0
Summary: A Mistake
Author-email: Elliot <captainexpo@gmail.com>
License: MIT
Project-URL: Homepage, https://github.com/Captainexpo-1/Mistake-Lang
Project-URL: Source, https://github.com/Captainexpo-1/Mistake-Lang
Project-URL: Tracker, https://github.com/Captainexpo-1/Mistake-Lang/issues
Requires-Python: >=3.7
License-File: LICENSE
Requires-Dist: annotated-types==0.7.0
Requires-Dist: anyio==4.8.0
Requires-Dist: build==1.2.2.post1
Requires-Dist: certifi==2024.12.14
Requires-Dist: cffi==1.17.1
Requires-Dist: charset-normalizer==3.4.1
Requires-Dist: future==1.0.0
Requires-Dist: gevent==24.11.1
Requires-Dist: greenlet==3.1.1
Requires-Dist: h11==0.14.0
Requires-Dist: h2==4.1.0
Requires-Dist: hpack==4.0.0
Requires-Dist: httpcore==1.0.7
Requires-Dist: httpx==0.28.1
Requires-Dist: hyperframe==6.0.1
Requires-Dist: requests==2.32.3
Requires-Dist: idna==3.10
Requires-Dist: inflection==0.5.1
Requires-Dist: packaging==24.2
Requires-Dist: pyairtable==3.0.1
Requires-Dist: pyproject_hooks==1.2.0
Requires-Dist: python-dotenv==1.0.1
Requires-Dist: setuptools==75.8.0
Requires-Dist: sniffio==1.3.1
Requires-Dist: typing_extensions==4.12.2
Requires-Dist: urllib3==2.3.0
Requires-Dist: zope.event==5.0
Requires-Dist: zope.interface==7.2
Provides-Extra: vulkan
Requires-Dist: kp==0.9.0; extra == "vulkan"
Requires-Dist: vulkan; extra == "vulkan"
Requires-Dist: numpy==1.26.4; extra == "vulkan"
